nion/experimental/Wizard.py
nion/experimental/__init__.py
nion/experimental/py.typed
nion/experimental/test/Wizard_test.py
nion/experimental/test/__init__.py
nionswift_experimental-0.7.19.dist-info/licenses/LICENSE
nionswift_plugin/drift_correction/__init__.py
nionswift_plugin/drift_correction/drift_correction.py
nionswift_plugin/drift_correction/settings_dialog.py
nionswift_plugin/drift_correction/resources/help_icon_24.png
nionswift_plugin/drift_correction/resources/sliders_icon_24.png
nionswift_plugin/drift_correction/resources/html/genindex.html
nionswift_plugin/drift_correction/resources/html/index.html
nionswift_plugin/drift_correction/resources/html/manual.html
nionswift_plugin/drift_correction/resources/html/search.html
nionswift_plugin/drift_correction/resources/html/searchindex.js
nionswift_plugin/drift_correction/resources/html/_images/drift_correction_main_window.png
nionswift_plugin/drift_correction/resources/html/_images/drift_correction_settings_window.png
nionswift_plugin/drift_correction/resources/html/_static/basic.css
nionswift_plugin/drift_correction/resources/html/_static/doctools.js
nionswift_plugin/drift_correction/resources/html/_static/documentation_options.js
nionswift_plugin/drift_correction/resources/html/_static/file.png
nionswift_plugin/drift_correction/resources/html/_static/jquery-3.5.1.js
nionswift_plugin/drift_correction/resources/html/_static/jquery.js
nionswift_plugin/drift_correction/resources/html/_static/language_data.js
nionswift_plugin/drift_correction/resources/html/_static/minus.png
nionswift_plugin/drift_correction/resources/html/_static/nature.css
nionswift_plugin/drift_correction/resources/html/_static/plus.png
nionswift_plugin/drift_correction/resources/html/_static/pygments.css
nionswift_plugin/drift_correction/resources/html/_static/searchtools.js
nionswift_plugin/drift_correction/resources/html/_static/underscore-1.12.0.js
nionswift_plugin/drift_correction/resources/html/_static/underscore-1.13.1.js
nionswift_plugin/drift_correction/resources/html/_static/underscore.js
nionswift_experimental-0.7.19.dist-info/METADATA
nionswift_experimental-0.7.19.dist-info/WHEEL
nionswift_experimental-0.7.19.dist-info/top_level.txt
nionswift_experimental-0.7.19.dist-info/RECORD
