Metadata-Version: 2.4
Name: nionswift-experimental
Version: 0.7.19
Summary: Experimental tools package for Nion Swift.
Home-page: https://github.com/nion-software/experimental
Author: Nion Software
Author-email: swift@nion.com
License: GPL-3.0-only
Classifier: Development Status :: 4 - Beta
Classifier: License :: OSI Approved :: GNU General Public License v3 (GPLv3)
Classifier: Programming Language :: Python :: 3.11
Classifier: Programming Language :: Python :: 3.12
Classifier: Programming Language :: Python :: 3.13
Requires-Python: >=3.11
License-File: LICENSE
Requires-Dist: nionswift<17.0,>=16.16
Requires-Dist: niondata<16.0,>=15.9
Requires-Dist: nionui<11.0,>=10.2
Dynamic: license-file
